sqlalchemy_filter_converter-1.4.0.dist-info/METADATA
sqlalchemy_filter_converter-1.4.0.dist-info/WHEEL
sqlalchemy_filter_converter-1.4.0.dist-info/entry_points.txt
sqlalchemy_filter_converter-1.4.0.dist-info/licenses/LICENSE
sqlalchemy_filter_converter/__init__.py
sqlalchemy_filter_converter/converters/__init__.py
sqlalchemy_filter_converter/converters/advanced.py
sqlalchemy_filter_converter/converters/base.py
sqlalchemy_filter_converter/converters/django.py
sqlalchemy_filter_converter/converters/simple.py
sqlalchemy_filter_converter/exc.py
sqlalchemy_filter_converter/ext/__init__.py
sqlalchemy_filter_converter/ext/fastapi.py
sqlalchemy_filter_converter/guards.py
sqlalchemy_filter_converter/lookups.py
sqlalchemy_filter_converter/operators.py
sqlalchemy_filter_converter/py.typed
sqlalchemy_filter_converter/types.py
sqlalchemy_filter_converter/utils.py
sqlalchemy_filter_converter-1.4.0.dist-info/RECORD
