Metadata-Version: 2.1
Name: sqlalchemy_filter_converter
Version: 1.4.0
Summary: SQLAlchemy filter converters.
Author-Email: Dmitriy Lunev <dima.lunev14@gmail.com>
License: MIT
Requires-Python: >=3.11
Requires-Dist: sqlalchemy>=2.0
Requires-Dist: python-dev-utils>=7.0.1
Requires-Dist: sqlalchemy-dev-utils>=1.2.0
Provides-Extra: fastapi
Requires-Dist: fastapi; extra == "fastapi"
